snowflet/__init__.py
snowflet/_version.py
snowflet/db.py
snowflet/lib.py
snowflet/pipeline.py
snowflet/toolkit.py
snowflet-0.0.2.dist-info/LICENSE
snowflet-0.0.2.dist-info/METADATA
snowflet-0.0.2.dist-info/WHEEL
snowflet-0.0.2.dist-info/top_level.txt
snowflet-0.0.2.dist-info/RECORD
