Metadata-Version: 2.1
Name: snowflet
Version: 0.0.2
Summary: Data engineering & Data science Pipeline Framework
Home-page: https://github.com/bluefloyd00/snowflet
Author: Simone Fiorentini
Author-email: simone.fiorentini@gmail.com
License: UNKNOWN
Platform: UNKNOWN
Classifier: Programming Language :: Python :: 3
Classifier: Natural Language :: English
Classifier: License :: OSI Approved :: MIT License
Classifier: Operating System :: OS Independent
Requires-Python: >=3.6
Requires-Dist: wheel
Requires-Dist: PyYAML (==5.3.1)
Requires-Dist: snowflake-sqlalchemy
Requires-Dist: numpy
Requires-Dist: pandas
Requires-Dist: nltk
Requires-Dist: versioneer
